setup.py
value_object/__init__.py
value_object/encoder.py
value_object/helper.py
value_object/value_object.py
value_object.egg-info/PKG-INFO
value_object.egg-info/SOURCES.txt
value_object.egg-info/dependency_links.txt
value_object.egg-info/top_level.txt