Metadata-Version: 1.0
Name: value-object
Version: 0.1.3
Summary: Tiny implementation of Value Object of Eric Evans DDD
Home-page: http://blog.mikamix.net
Author: mikamix
Author-email: tmp@mikamix.net
License: BSD
Keywords: value object,ddd,domain driven design
Platform: any
Classifier: Development Status :: 2 - Pre-Alpha
Classifier: License :: OSI Approved :: BSD License
Classifier: Programming Language :: Python
